py_clickhouse_migrator/__init__.py
py_clickhouse_migrator/cli.py
py_clickhouse_migrator/migrator.py
py_clickhouse_migrator-0.3.dist-info/LICENCE.txt
py_clickhouse_migrator-0.3.dist-info/METADATA
py_clickhouse_migrator-0.3.dist-info/WHEEL
py_clickhouse_migrator-0.3.dist-info/entry_points.txt
py_clickhouse_migrator-0.3.dist-info/top_level.txt
py_clickhouse_migrator-0.3.dist-info/RECORD
