Metadata-Version: 2.1
Name: py-clickhouse-migrator
Version: 0.3
Summary: Simple tool for manage ClickHouse migrations.
Author: Maksim Burtsev
Author-email: zadrot-lol@list.ru
License: MIT
Classifier: Operating System :: OS Independent
License-File: LICENCE.txt
Requires-Dist: click >=8.0.1
Requires-Dist: clickhouse-driver >=0.2.0
Requires-Dist: python-dotenv >=1.0.0
